chpwd_cmd/__init__.py
chpwd_cmd/arguments.py
chpwd_cmd/chpwd_cmd.py
chpwd_cmd/color.py
chpwd_cmd/config_file.py
chpwd_cmd/workdir.py
chpwd_cmd-0.0.2.dist-info/LICENSE
chpwd_cmd-0.0.2.dist-info/METADATA
chpwd_cmd-0.0.2.dist-info/WHEEL
chpwd_cmd-0.0.2.dist-info/entry_points.txt
chpwd_cmd-0.0.2.dist-info/top_level.txt
chpwd_cmd-0.0.2.dist-info/RECORD
