Metadata-Version: 2.1
Name: chpwd-cmd
Version: 0.0.2
Summary: Execute the commands in the configuration file according to the current working directory.
Home-page: https://github.com/teddyyy/chpwd_cmd
Author: KIMOTO Mizuki
Author-email: teddy@sfc.wide.ad.jp
License: MIT
Platform: UNKNOWN
Classifier: Programming Language :: Python :: 3.7
Classifier: Programming Language :: Python :: 3.8
Requires-Dist: toml (==0.10.1)
Requires-Dist: schema (==0.7.2)
